LICENSE
README.md
setup.py
jinja2_rendervars/__init__.py
jinja2_rendervars/_contextvars.c
jinja2_rendervars.egg-info/PKG-INFO
jinja2_rendervars.egg-info/SOURCES.txt
jinja2_rendervars.egg-info/dependency_links.txt
jinja2_rendervars.egg-info/top_level.txt