Metadata-Version: 2.1
Name: jinja2-rendervars
Version: 0.1
Summary: Use Jinja templates to render more than just strings.
Home-page: https://github.com/wagnerflo/jinja2_rendervars
Author: Florian Wagner
Author-email: florian@wagner-flo.net
License: UNKNOWN
Platform: UNKNOWN
Classifier: Development Status :: 4 - Beta
Classifier: Environment :: Plugins
Classifier: Intended Audience :: Developers
Classifier: License :: OSI Approved :: Apache Software License
Classifier: Programming Language :: C
Classifier: Programming Language :: Python :: 3 :: Only
Classifier: Topic :: Text Processing
Requires-Python: >=3.7
